_config.py
_main.py
application/__init__.py
application/core/gemini_model.py
application/core/github_api.py
application/utils/api.py
application/utils/callbacks.py
application/utils/gemini_config.py
application/utils/parser.py
github_echo-0.0.7.dist-info/LICENSE
github_echo-0.0.7.dist-info/METADATA
github_echo-0.0.7.dist-info/WHEEL
github_echo-0.0.7.dist-info/entry_points.txt
github_echo-0.0.7.dist-info/top_level.txt
github_echo-0.0.7.dist-info/RECORD
