Metadata-Version: 2.1
Name: github-echo
Version: 0.0.7
Summary: A command-line tool built to obtain in-depth, actionable information about GitHub repositories.
Author-email: Aryan Khurana <aryankhurana1511@gmail.com>
Project-URL: Homepage, https://github.com/AryanK1511/github-echo
Project-URL: Issues, https://github.com/AryanK1511/github-echo/issues
Keywords: GitHub,GenAI,Python3,CLI
Classifier: Programming Language :: Python :: 3
Classifier: License :: OSI Approved :: MIT License
Classifier: Operating System :: OS Independent
Requires-Python: >=3.9
License-File: LICENSE
Requires-Dist: annotated-types ==0.7.0
Requires-Dist: anyio ==4.4.0
Requires-Dist: backports.tarfile ==1.2.0
Requires-Dist: build ==1.2.2
Requires-Dist: cachetools ==5.5.0
Requires-Dist: certifi ==2024.8.30
Requires-Dist: charset-normalizer ==3.3.2
Requires-Dist: click ==8.1.7
Requires-Dist: docutils ==0.21.2
Requires-Dist: google-ai-generativelanguage ==0.6.6
Requires-Dist: google-api-core ==2.19.2
Requires-Dist: google-api-python-client ==2.144.0
Requires-Dist: google-auth ==2.34.0
Requires-Dist: google-auth-httplib2 ==0.2.0
Requires-Dist: google-generativeai ==0.7.2
Requires-Dist: googleapis-common-protos ==1.65.0
Requires-Dist: grpcio ==1.66.1
Requires-Dist: grpcio-status ==1.62.3
Requires-Dist: h11 ==0.14.0
Requires-Dist: httpcore ==1.0.5
Requires-Dist: httplib2 ==0.22.0
Requires-Dist: httpx ==0.27.2
Requires-Dist: idna ==3.8
Requires-Dist: importlib-metadata ==8.4.0
Requires-Dist: jaraco.classes ==3.4.0
Requires-Dist: jaraco.context ==6.0.1
Requires-Dist: jaraco.functools ==4.0.2
Requires-Dist: keyring ==25.3.0
Requires-Dist: markdown-it-py ==3.0.0
Requires-Dist: mdurl ==0.1.2
Requires-Dist: more-itertools ==10.5.0
Requires-Dist: nh3 ==0.2.18
Requires-Dist: numpy ==2.1.1
Requires-Dist: packaging ==24.1
Requires-Dist: pkginfo ==1.10.0
Requires-Dist: proto-plus ==1.24.0
Requires-Dist: protobuf ==4.25.4
Requires-Dist: pyasn1 ==0.6.0
Requires-Dist: pyasn1-modules ==0.4.0
Requires-Dist: pydantic ==2.9.0
Requires-Dist: pydantic-core ==2.23.2
Requires-Dist: Pygments ==2.18.0
Requires-Dist: pyparsing ==3.1.4
Requires-Dist: pyproject-hooks ==1.1.0
Requires-Dist: python-dateutil ==2.9.0.post0
Requires-Dist: python-dotenv ==1.0.1
Requires-Dist: pytz ==2024.1
Requires-Dist: readme-renderer ==44.0
Requires-Dist: requests ==2.32.3
Requires-Dist: requests-toolbelt ==1.0.0
Requires-Dist: rfc3986 ==2.0.0
Requires-Dist: rich ==13.8.0
Requires-Dist: rsa ==4.9
Requires-Dist: ruff ==0.6.4
Requires-Dist: shellingham ==1.5.4
Requires-Dist: six ==1.16.0
Requires-Dist: sniffio ==1.3.1
Requires-Dist: tomli ==2.0.1
Requires-Dist: tqdm ==4.66.5
Requires-Dist: twine ==5.1.1
Requires-Dist: typer ==0.12.5
Requires-Dist: typing-extensions ==4.12.2
Requires-Dist: tzdata ==2024.1
Requires-Dist: uritemplate ==4.1.1
Requires-Dist: urllib3 ==2.2.2
Requires-Dist: zipp ==3.20.1
